pypetwalk/__init__.py
pypetwalk/__version__.py
pypetwalk/const.py
pypetwalk/exceptions.py
pypetwalk/py.typed
pypetwalk/pypetwalk.py
pypetwalk/api/__init__.py
pypetwalk/api/api.py
pypetwalk/aws/__init__.py
pypetwalk/aws/aws.py
pypetwalk/aws/event.py
pypetwalk/aws/pet.py
pypetwalk/ws/__init__.py
pypetwalk/ws/request.py
pypetwalk/ws/ws.py
pypetwalk-1.1.2.dist-info/LICENSE
pypetwalk-1.1.2.dist-info/METADATA
pypetwalk-1.1.2.dist-info/WHEEL
pypetwalk-1.1.2.dist-info/top_level.txt
pypetwalk-1.1.2.dist-info/RECORD
