Metadata-Version: 2.1
Name: pypetwalk
Version: 1.1.2
Summary: Python library to communicate with the petWALK.control module
Home-page: https://github.com/p0l0/pypetwalk
Download-URL: https://github.com/p0l0/pypetwalk/tarball/1.1.2
Author: Marco Neumann
Author-email: pypetwalk@binware.dev
License: MIT License
Keywords: petwalk,petwalk.control,home,automation
Platform: any
Classifier: Development Status :: 5 - Production/Stable
Classifier: Intended Audience :: Developers
Classifier: License :: OSI Approved :: MIT License
Classifier: Operating System :: OS Independent
Classifier: Programming Language :: Python :: 3.11
Classifier: Programming Language :: Python :: 3.12
Classifier: Topic :: Home Automation
Requires-Python: >=3.11
License-File: LICENSE
Requires-Dist: aiohttp >=3.8.1
Requires-Dist: pycognito ==2023.5.0
